gcaa/__init__.py
gcaa/algorithms/__init__.py
gcaa/algorithms/greedy.py
gcaa/core/__init__.py
gcaa/core/control.py
gcaa/core/dta.py
gcaa/core/utility.py
gcaa/tests/__init__.py
gcaa/tests/test_arrays.py
gcaa/tests/test_basic.py
gcaa/tests/test_disk.py
gcaa/tests/test_dta.py
gcaa/tests/test_hardware.py
gcaa/tests/test_logger.py
gcaa/tests/test_serialize.py
gcaa/tools/__init__.py
gcaa/tools/arrays.py
gcaa/tools/basic.py
gcaa/tools/constants.py
gcaa/tools/dates.py
gcaa/tools/disk.py
gcaa/tools/hardware.py
gcaa/tools/logs.py
gcaa/tools/notebooks.py
gcaa/tools/plotting.py
gcaa/tools/serialize.py
gcaa/tools/system.py
gcaa/tools/timer.py
gcaa/tools/winners.py
gcaa-1.0.0.dist-info/licenses/LICENSE
gcaa-1.0.0.dist-info/METADATA
gcaa-1.0.0.dist-info/WHEEL
gcaa-1.0.0.dist-info/top_level.txt
gcaa-1.0.0.dist-info/RECORD
